{"state":"NV","stateName":"Nevada","naep":{"text":"8 out of 10","numerator":8,"denominator":10},"schools":[{"name":"Nevada Virtual Academy","x":204.5,"y":271.6,"proficiency":0.13,"district":"STATE-SPONSORED CHARTER SCHOOLS","city":"Las Vegas"},{"name":"Coral Academy Sandy Ridge","x":204.7,"y":272.5,"proficiency":0.52,"district":"STATE-SPONSORED CHARTER SCHOOLS","city":"Henderson"},{"name":"Quest Academy Northwest","x":203.7,"y":267.6,"proficiency":0.05,"district":"STATE-SPONSORED CHARTER SCHOOLS","city":"Las Vegas"},{"name":"Silver Sands Montessori","x":205.4,"y":271,"proficiency":0.3,"district":"STATE-SPONSORED CHARTER SCHOOLS","city":"Henderson"},{"name":"Elko Institute for Academic Achievement","x":213.8,"y":181.1,"proficiency":0.495,"district":"STATE-SPONSORED CHARTER SCHOOLS","city":"Elko"},{"name":"Oasis Academy","x":166.3,"y":196.5,"proficiency":0.545,"district":"STATE-SPONSORED CHARTER SCHOOLS","city":"Fallon"},{"name":"Discovery Charter School HillPointe","x":202.6,"y":268.1,"proficiency":0.1,"district":"STATE-SPONSORED CHARTER SCHOOLS","city":"Las Vegas"},{"name":"Somerset Academy Sky Pointe","x":203.2,"y":266.5,"proficiency":0.42,"district":"STATE-SPONSORED CHARTER SCHOOLS","city":"Las Vegas"},{"name":"Pinecrest Academy of Nevada Cadence","x":206.6,"y":271.8,"proficiency":0.37,"district":"STATE-SPONSORED CHARTER SCHOOLS","city":"Henderson"},{"name":"Honors Academy of Literature","x":152.3,"y":192.1,"proficiency":0.495,"district":"STATE-SPONSORED CHARTER SCHOOLS","city":"Reno"},{"name":"Doral Academy Red Rock","x":201.3,"y":268.4,"proficiency":0.27,"district":"STATE-SPONSORED CHARTER SCHOOLS","city":"Las Vegas"},{"name":"Learning Bridge","x":220.3,"y":212.9,"proficiency":0.1,"district":"STATE-SPONSORED CHARTER SCHOOLS","city":"Ely"},{"name":"Freedom Classical Academy K-8","x":205.2,"y":267.4,"proficiency":0.27,"district":"STATE-SPONSORED CHARTER SCHOOLS","city":"North Las Vegas"},{"name":"Founders Academy of Las Vegas","x":203.7,"y":267.6,"proficiency":0.05,"district":"STATE-SPONSORED CHARTER SCHOOLS","city":"Las Vegas"},{"name":"Amplus Durango","x":202.4,"y":270.4,"proficiency":0.42,"district":"STATE-SPONSORED CHARTER SCHOOLS","city":"Las Vegas"},{"name":"Mater Mountain Vista","x":205.5,"y":270,"proficiency":0.22,"district":"STATE-SPONSORED CHARTER SCHOOLS","city":"Las Vegas"},{"name":"Equipo Academy","x":205.5,"y":269.2,"proficiency":0.075,"district":"STATE-SPONSORED CHARTER SCHOOLS","city":"Las Vegas"},{"name":"Sports Leadership and Management Academy","x":205.8,"y":271,"proficiency":0.12,"district":"STATE-SPONSORED CHARTER SCHOOLS","city":"Henderson"},{"name":"Democracy Prep at Agassi Middle","x":204.6,"y":268.5,"proficiency":0.05,"district":"STATE-SPONSORED CHARTER SCHOOLS","city":"Las Vegas"},{"name":"Leadership Academy of Nevada","x":203.4,"y":266.8,"proficiency":0.345,"district":"STATE-SPONSORED CHARTER SCHOOLS","city":"Las Vegas"},{"name":"Doral Academy Cactus","x":201.9,"y":271.8,"proficiency":0.47,"district":"STATE-SPONSORED CHARTER SCHOOLS","city":"Las Vegas"},{"name":"Doral Academy of Northern Nevada","x":152.2,"y":194.7,"proficiency":0.47,"district":"STATE-SPONSORED CHARTER SCHOOLS","city":"Reno"},{"name":"Doral Academy West Pebble","x":202.8,"y":271.4,"proficiency":0.27,"district":"STATE-SPONSORED CHARTER SCHOOLS","city":"Las Vegas"},{"name":"Doral Academy Fire Mesa","x":203.1,"y":268,"proficiency":0.32,"district":"STATE-SPONSORED CHARTER SCHOOLS","city":"Las Vegas"},{"name":"Legacy Traditional School North Valley","x":204.2,"y":267.4,"proficiency":0.22,"district":"STATE-SPONSORED CHARTER SCHOOLS","city":"North Las Vegas"},{"name":"Mater Academy of Northern Nevada","x":152.9,"y":192,"proficiency":0.1,"district":"STATE-SPONSORED CHARTER SCHOOLS","city":"Reno"},{"name":"Somerset Academy Losee","x":205.4,"y":267.7,"proficiency":0.12,"district":"STATE-SPONSORED CHARTER SCHOOLS","city":"North Las Vegas"},{"name":"Pinecrest Academy of Nevada St Rose","x":204.2,"y":272.2,"proficiency":0.37,"district":"STATE-SPONSORED CHARTER SCHOOLS","city":"Las Vegas"},{"name":"Somerset Academy Lone Mountain","x":203.5,"y":267.4,"proficiency":0.37,"district":"STATE-SPONSORED CHARTER SCHOOLS","city":"Las Vegas"},{"name":"Mater Bonanza","x":205.8,"y":269.2,"proficiency":0.17,"district":"STATE-SPONSORED CHARTER SCHOOLS","city":"Las Vegas"},{"name":"Somerset Academy North Las Vegas","x":205,"y":267.1,"proficiency":0.12,"district":"STATE-SPONSORED CHARTER SCHOOLS","city":"North Las Vegas"},{"name":"Doral Academy Saddle","x":202.1,"y":269.6,"proficiency":0.27,"district":"STATE-SPONSORED CHARTER SCHOOLS","city":"Las Vegas"},{"name":"Coral Academy Nellis AFB","x":206.1,"y":267.9,"proficiency":0.245,"district":"STATE-SPONSORED CHARTER SCHOOLS","city":"Las Vegas"},{"name":"Coral Academy Centennial Hills","x":203.3,"y":266.6,"proficiency":0.545,"district":"STATE-SPONSORED CHARTER SCHOOLS","city":"Las Vegas"},{"name":"Pinecrest Academy of Nevada Inspirada","x":204.2,"y":273.5,"proficiency":0.77,"district":"STATE-SPONSORED CHARTER SCHOOLS","city":"Henderson"},{"name":"Somerset Academy Stephanie","x":205.6,"y":271.9,"proficiency":0.27,"district":"STATE-SPONSORED CHARTER SCHOOLS","city":"Henderson"},{"name":"Somerset Academy Skye Canyon","x":202.5,"y":265.9,"proficiency":0.37,"district":"STATE-SPONSORED CHARTER SCHOOLS","city":"Las Vegas"},{"name":"Legacy Traditional School Cadence","x":206.8,"y":271.6,"proficiency":0.32,"district":"STATE-SPONSORED CHARTER SCHOOLS","city":"Henderson"},{"name":"Somerset Academy Aliante","x":204.3,"y":266.9,"proficiency":0.22,"district":"STATE-SPONSORED CHARTER SCHOOLS","city":"North Las Vegas"},{"name":"Nevada Prep Charter School","x":206,"y":268.9,"proficiency":0.245,"district":"STATE-SPONSORED CHARTER SCHOOLS","city":"Las Vegas"},{"name":"Legacy Traditional School Southwest Las Vegas","x":202.6,"y":271.3,"proficiency":0.27,"district":"STATE-SPONSORED CHARTER SCHOOLS","city":"Las Vegas"},{"name":"Signature Preparatory","x":206.6,"y":272.1,"proficiency":0.1,"district":"STATE-SPONSORED CHARTER SCHOOLS","city":"Henderson"},{"name":"Pinecrest Academy of Nevada Sloan Canyon","x":203.8,"y":272.9,"proficiency":0.37,"district":"STATE-SPONSORED CHARTER SCHOOLS","city":"Henderson"},{"name":"Explore Academy","x":203.6,"y":267.4,"proficiency":0.245,"district":"STATE-SPONSORED CHARTER SCHOOLS","city":"Las Vegas"},{"name":"Mater Academy East","x":205.4,"y":269.1,"proficiency":0.12,"district":"STATE-SPONSORED CHARTER SCHOOLS","city":"Las Vegas"},{"name":"Davidson Academy","x":152.4,"y":191.9,"proficiency":0.9,"district":"DAVIDSON ACADEMY  SCHOOL DISTRICT","city":"Reno"},{"name":"Churchill County Middle School","x":166.5,"y":196.7,"proficiency":0.12,"district":"CHURCHILL COUNTY SCHOOL DISTRICT","city":"Fallon"},{"name":"Woodbury  C W MS","x":205.2,"y":270.4,"proficiency":0.075,"district":"CLARK COUNTY SCHOOL DISTRICT","city":"Las Vegas"},{"name":"Robison  Dell H MS","x":205.8,"y":269.1,"proficiency":0.025,"district":"CLARK COUNTY SCHOOL DISTRICT","city":"Las Vegas"},{"name":"Von Tobel  Ed MS","x":205.5,"y":268.5,"proficiency":0.12,"district":"CLARK COUNTY SCHOOL DISTRICT","city":"Las Vegas"},{"name":"Garside  Frank F JHS","x":203.3,"y":268.8,"proficiency":0.075,"district":"CLARK COUNTY SCHOOL DISTRICT","city":"Las Vegas"},{"name":"Cannon  Helen C JHS","x":204.7,"y":270.7,"proficiency":0.025,"district":"CLARK COUNTY SCHOOL DISTRICT","city":"Las Vegas"},{"name":"Hyde Park MS","x":203.9,"y":269,"proficiency":0.42,"district":"CLARK COUNTY SCHOOL DISTRICT","city":"Las Vegas"},{"name":"Brinley  J Harold MS","x":203.6,"y":268.1,"proficiency":0.06,"district":"CLARK COUNTY SCHOOL DISTRICT","city":"Las Vegas"},{"name":"Cashman  James MS","x":203.6,"y":269.6,"proficiency":0.12,"district":"CLARK COUNTY SCHOOL DISTRICT","city":"Las Vegas"},{"name":"Bridger  Jim MS","x":205,"y":268.4,"proficiency":0.075,"district":"CLARK COUNTY SCHOOL DISTRICT","city":"N  Las Vegas"},{"name":"Fremont  John C Professional Dev MS","x":204.6,"y":269.5,"proficiency":0.05,"district":"CLARK COUNTY SCHOOL DISTRICT","city":"Las Vegas"},{"name":"Knudson  K O Academy of the Arts","x":205,"y":269.6,"proficiency":0.12,"district":"CLARK COUNTY SCHOOL DISTRICT","city":"Las Vegas"},{"name":"Swainston  Theron L MS","x":204.3,"y":267.8,"proficiency":0.075,"district":"CLARK COUNTY SCHOOL DISTRICT","city":"N  Las Vegas"},{"name":"Gibson  Robert O MS Leadership Academy","x":203.9,"y":268.7,"proficiency":0.12,"district":"CLARK COUNTY SCHOOL DISTRICT","city":"Las Vegas"},{"name":"Variety J-SHS","x":205.1,"y":269.2,"proficiency":0.245,"district":"CLARK COUNTY SCHOOL DISTRICT","city":"Las Vegas"},{"name":"Orr  William E MS","x":204.7,"y":270,"proficiency":0.025,"district":"CLARK COUNTY SCHOOL DISTRICT","city":"Las Vegas"},{"name":"White  Thurman Academy of the Arts MS","x":205.5,"y":271,"proficiency":0.22,"district":"CLARK COUNTY SCHOOL DISTRICT","city":"Henderson"},{"name":"Becker  Ernest MS","x":202.6,"y":268,"proficiency":0.17,"district":"CLARK COUNTY SCHOOL DISTRICT","city":"Las Vegas"},{"name":"Sawyer  Grant MS","x":203,"y":270.2,"proficiency":0.12,"district":"CLARK COUNTY SCHOOL DISTRICT","city":"Las Vegas"},{"name":"Lyon  Mack MS","x":216.2,"y":264.2,"proficiency":0.47,"district":"CLARK COUNTY SCHOOL DISTRICT","city":"Overton"},{"name":"Guinn  Kenny C MS","x":203.1,"y":269.8,"proficiency":0.27,"district":"CLARK COUNTY SCHOOL DISTRICT","city":"Las Vegas"},{"name":"Garrett  Elton M JHS","x":208.5,"y":273.7,"proficiency":0.22,"district":"CLARK COUNTY SCHOOL DISTRICT","city":"Boulder City"},{"name":"Brown  B Mahlon JHS","x":207,"y":271.8,"proficiency":0.17,"district":"CLARK COUNTY SCHOOL DISTRICT","city":"Henderson"},{"name":"Sandy Valley J-SHS","x":196.5,"y":274.2,"proficiency":0.1,"district":"CLARK COUNTY SCHOOL DISTRICT","city":"Sandy Valley"},{"name":"Greenspun  Barbara & Hank JHS","x":205.3,"y":271.8,"proficiency":0.32,"district":"CLARK COUNTY SCHOOL DISTRICT","city":"Henderson"},{"name":"Johnson  Walter JHS Academy of Int'l Studies","x":202.9,"y":268.7,"proficiency":0.32,"district":"CLARK COUNTY SCHOOL DISTRICT","city":"Las Vegas"},{"name":"O'Callaghan  Mike MS i3 Learn Academy","x":206.5,"y":269.1,"proficiency":0.32,"district":"CLARK COUNTY SCHOOL DISTRICT","city":"Las Vegas"},{"name":"Laughlin J-SHS","x":208.7,"y":289.2,"proficiency":0.05,"district":"CLARK COUNTY SCHOOL DISTRICT","city":"Laughlin"},{"name":"West Preparatory Institute J-SHS","x":204.4,"y":268.5,"proficiency":0.05,"district":"CLARK COUNTY SCHOOL DISTRICT","city":"Las Vegas"},{"name":"Lied STEM Academy MS","x":204,"y":267,"proficiency":0.33,"district":"CLARK COUNTY SCHOOL DISTRICT","city":"Las Vegas"},{"name":"Keller  Duane D MS","x":206.2,"y":269.4,"proficiency":0.025,"district":"CLARK COUNTY SCHOOL DISTRICT","city":"Las Vegas"},{"name":"Molasky  Irwin & Susan JHS","x":203.1,"y":267.6,"proficiency":0.075,"district":"CLARK COUNTY SCHOOL DISTRICT","city":"Las Vegas"},{"name":"Silvestri  Charles JHS","x":204.1,"y":271.9,"proficiency":0.17,"district":"CLARK COUNTY SCHOOL DISTRICT","city":"Las Vegas"},{"name":"Cortney  Francis H JHS","x":205.6,"y":270.7,"proficiency":0.075,"district":"CLARK COUNTY SCHOOL DISTRICT","city":"Las Vegas"},{"name":"Lawrence  Clifford J JHS","x":202.4,"y":269.8,"proficiency":0.12,"district":"CLARK COUNTY SCHOOL DISTRICT","city":"Las Vegas"},{"name":"Miller  Bob MS","x":204.8,"y":272.1,"proficiency":0.42,"district":"CLARK COUNTY SCHOOL DISTRICT","city":"Henderson"},{"name":"Rogich  Sig MS","x":201.9,"y":268.4,"proficiency":0.37,"district":"CLARK COUNTY SCHOOL DISTRICT","city":"Las Vegas"},{"name":"Leavitt  Justice Myron E MS","x":203.2,"y":267.3,"proficiency":0.22,"district":"CLARK COUNTY SCHOOL DISTRICT","city":"Las Vegas"},{"name":"Cram  Brian & Teri MS","x":204.7,"y":266.8,"proficiency":0.22,"district":"CLARK COUNTY SCHOOL DISTRICT","city":"N  Las Vegas"},{"name":"Monaco  Mario C & JoAnne MS","x":205.9,"y":268.8,"proficiency":0.025,"district":"CLARK COUNTY SCHOOL DISTRICT","city":"Las Vegas"},{"name":"Schofield  Jack Lund MS","x":204.4,"y":271.6,"proficiency":0.12,"district":"CLARK COUNTY SCHOOL DISTRICT","city":"Las Vegas"},{"name":"Sedway  Marvin M MS","x":204.8,"y":268.1,"proficiency":0.075,"district":"CLARK COUNTY SCHOOL DISTRICT","city":"N  Las Vegas"},{"name":"Harney  Kathleen & Tim MS","x":206.4,"y":269.7,"proficiency":0.17,"district":"CLARK COUNTY SCHOOL DISTRICT","city":"Las Vegas"},{"name":"Fertitta  Victoria MS","x":201.9,"y":270,"proficiency":0.27,"district":"CLARK COUNTY SCHOOL DISTRICT","city":"Las Vegas"},{"name":"Saville  Anthony MS","x":203.8,"y":266.2,"proficiency":0.22,"district":"CLARK COUNTY SCHOOL DISTRICT","city":"Las Vegas"},{"name":"Findlay  Clifford O MS","x":205,"y":267.2,"proficiency":0.075,"district":"CLARK COUNTY SCHOOL DISTRICT","city":"N  Las Vegas"},{"name":"Mannion  Jack & Terry MS","x":206.4,"y":272.8,"proficiency":0.32,"district":"CLARK COUNTY SCHOOL DISTRICT","city":"Henderson"},{"name":"Cadwallader  Ralph MS","x":203.4,"y":266.5,"proficiency":0.32,"district":"CLARK COUNTY SCHOOL DISTRICT","city":"Las Vegas"},{"name":"Canarelli  Lawrence & Heidi MS","x":202.9,"y":271,"proficiency":0.27,"district":"CLARK COUNTY SCHOOL DISTRICT","city":"Las Vegas"},{"name":"Hughes  Charles Arthur MS","x":222.4,"y":260.5,"proficiency":0.22,"district":"CLARK COUNTY SCHOOL DISTRICT","city":"Mesquite"},{"name":"Webb  Del E MS","x":204.8,"y":272.7,"proficiency":0.47,"district":"CLARK COUNTY SCHOOL DISTRICT","city":"Henderson"},{"name":"Mack  Jerome MS","x":205.5,"y":269.7,"proficiency":0.05,"district":"CLARK COUNTY SCHOOL DISTRICT","city":"Las Vegas"},{"name":"Bailey  Dr William H MS","x":206.5,"y":268.7,"proficiency":0.025,"district":"CLARK COUNTY SCHOOL DISTRICT","city":"Las Vegas"},{"name":"Johnston  Carroll M MS","x":205.3,"y":267.3,"proficiency":0.075,"district":"CLARK COUNTY SCHOOL DISTRICT","city":"N  Las Vegas"},{"name":"Odyssey Charter Schools 6-8 MS","x":203.4,"y":269.2,"proficiency":0.22,"district":"CLARK COUNTY SCHOOL DISTRICT","city":"Las Vegas"},{"name":"Indian Springs MS","x":198.4,"y":260,"proficiency":0.1,"district":"CLARK COUNTY SCHOOL DISTRICT","city":"Indian Springs"},{"name":"Tarkanian  Lois & Jerry MS","x":202.9,"y":271.8,"proficiency":0.37,"district":"CLARK COUNTY SCHOOL DISTRICT","city":"Las Vegas"},{"name":"Explore Knowledge Academy J-SHS","x":205.4,"y":270.9,"proficiency":0.345,"district":"CLARK COUNTY SCHOOL DISTRICT","city":"Las Vegas"},{"name":"Faiss  Wilbur & Theresa MS","x":201.9,"y":270.6,"proficiency":0.12,"district":"CLARK COUNTY SCHOOL DISTRICT","city":"Las Vegas"},{"name":"Burkholder  Lyal MS","x":206.3,"y":272.1,"proficiency":0.12,"district":"CLARK COUNTY SCHOOL DISTRICT","city":"Henderson"},{"name":"Escobedo  Edmundo Eddie Sr MS","x":202.7,"y":266.5,"proficiency":0.16,"district":"CLARK COUNTY SCHOOL DISTRICT","city":"Las Vegas"},{"name":"The Delta Academy J-SHS","x":204.7,"y":268.2,"proficiency":0.075,"district":"CLARK COUNTY SCHOOL DISTRICT","city":"North Las Vegas"},{"name":"Innovations Int'l Charter J-SHS","x":204.6,"y":269.5,"proficiency":0.025,"district":"CLARK COUNTY SCHOOL DISTRICT","city":"Las Vegas"},{"name":"100 Academy of Engineering and Technology MS","x":204.5,"y":268.4,"proficiency":0.05,"district":"CLARK COUNTY SCHOOL DISTRICT","city":"N  Las Vegas"},{"name":"Stewart  Helen J","x":204.8,"y":270.1,"proficiency":0.245,"district":"CLARK COUNTY SCHOOL DISTRICT","city":"Las Vegas"},{"name":"NV Learning Academy J-SHS","x":205,"y":270.1,"proficiency":0.245,"district":"CLARK COUNTY SCHOOL DISTRICT","city":"Las Vegas"},{"name":"Carson Valley Middle School","x":150.5,"y":203,"proficiency":0.32,"district":"DOUGLAS COUNTY SCHOOL DISTRICT","city":"Gardnerville"},{"name":"George Whittell High School","x":148.2,"y":201,"proficiency":0.3,"district":"DOUGLAS COUNTY SCHOOL DISTRICT","city":"Zephyr Cove"},{"name":"Pau Wa Lu Middle School","x":150.7,"y":204.1,"proficiency":0.22,"district":"DOUGLAS COUNTY SCHOOL DISTRICT","city":"Gardnerville"},{"name":"Douglas Nevada Online","x":150.9,"y":202.8,"proficiency":0.3,"district":"DOUGLAS COUNTY SCHOOL DISTRICT","city":"Minden"},{"name":"Adobe Middle School","x":213.3,"y":180.8,"proficiency":0.13,"district":"ELKO COUNTY SCHOOL DISTRICT","city":"Elko"},{"name":"Spring Creek Middle School","x":215.1,"y":182.5,"proficiency":0.17,"district":"ELKO COUNTY SCHOOL DISTRICT","city":"Spring Creek"},{"name":"Carlin Jr High School","x":208.5,"y":182.3,"proficiency":0.1,"district":"ELKO COUNTY SCHOOL DISTRICT","city":"Carlin"},{"name":"Owyhee Jr High School","x":213.6,"y":159.7,"proficiency":0.1,"district":"ELKO COUNTY SCHOOL DISTRICT","city":"Owyhee"},{"name":"Wells Jr High School","x":225.7,"y":178.3,"proficiency":0.1,"district":"ELKO COUNTY SCHOOL DISTRICT","city":"Wells"},{"name":"Jackpot Jr High School","x":233,"y":163,"proficiency":0.245,"district":"ELKO COUNTY SCHOOL DISTRICT","city":"Jackpot"},{"name":"West Wendover Middle School","x":236.5,"y":187.7,"proficiency":0.075,"district":"ELKO COUNTY SCHOOL DISTRICT","city":"West Wendover"},{"name":"Northeastern Nevada Virtual Academy","x":213.7,"y":181,"proficiency":0.1,"district":"ELKO COUNTY SCHOOL DISTRICT","city":"Elko"},{"name":"Dyer Elementary School","x":168.4,"y":231.4,"proficiency":0.245,"district":"ESMERALDA COUNTY SCHOOL DISTRICT","city":"Dyer"},{"name":"Eureka County High School","x":205.8,"y":204.9,"proficiency":0.1,"district":"EUREKA COUNTY SCHOOL DISTRICT","city":"Eureka"},{"name":"Winnemucca Junior High School","x":187.5,"y":172.6,"proficiency":0.32,"district":"HUMBOLDT COUNTY SCHOOL DISTRICT","city":"Winnemucca"},{"name":"Eleanor Lemaire Junior High School","x":196.6,"y":181.1,"proficiency":0.17,"district":"LANDER COUNTY SCHOOL DISTRICT","city":"Battle Mountain"},{"name":"Meadow Valley Middle School","x":221.6,"y":241.2,"proficiency":0.245,"district":"LINCOLN COUNTY SCHOOL DISTRICT","city":"Panaca"},{"name":"Pahranagat Valley Middle School","x":208.8,"y":247,"proficiency":0.3,"district":"LINCOLN COUNTY SCHOOL DISTRICT","city":"Alamo"},{"name":"Smith Valley Schools","x":155.8,"y":207,"proficiency":0.1,"district":"LYON COUNTY SCHOOL DISTRICT","city":"Smith"},{"name":"Yerington Intermediate School","x":159,"y":204.2,"proficiency":0.17,"district":"LYON COUNTY SCHOOL DISTRICT","city":"Yerington"},{"name":"Dayton Intermediate School","x":154.3,"y":198.2,"proficiency":0.17,"district":"LYON COUNTY SCHOOL DISTRICT","city":"Dayton"},{"name":"Silver Stage Middle School","x":159.1,"y":196.4,"proficiency":0.17,"district":"LYON COUNTY SCHOOL DISTRICT","city":"Silver Springs"},{"name":"Silverland Middle School","x":161.2,"y":193.1,"proficiency":0.12,"district":"LYON COUNTY SCHOOL DISTRICT","city":"Fernley"},{"name":"Hawthorne Junior High","x":164.3,"y":214.5,"proficiency":0.05,"district":"MINERAL COUNTY SCHOOL DISTRICT","city":"Hawthorne"},{"name":"Rosemary Clarke Middle School","x":192.4,"y":264.3,"proficiency":0.17,"district":"NYE COUNTY SCHOOL DISTRICT","city":"Pahrump"},{"name":"Pathways Middle School","x":192.2,"y":266,"proficiency":0.1,"district":"NYE COUNTY SCHOOL DISTRICT","city":"Pahrump"},{"name":"Amargosa Valley Middle School","x":187,"y":257.6,"proficiency":0.245,"district":"NYE COUNTY SCHOOL DISTRICT","city":"Amargosa"},{"name":"Beatty Middle School","x":184,"y":250.4,"proficiency":0.245,"district":"NYE COUNTY SCHOOL DISTRICT","city":"Beatty"},{"name":"Tonopah Middle School","x":182.1,"y":227.7,"proficiency":0.1,"district":"NYE COUNTY SCHOOL DISTRICT","city":"Tonopah"},{"name":"Carson Middle School","x":151.2,"y":198.8,"proficiency":0.19,"district":"CARSON CITY SCHOOL DISTRICT","city":"Carson City"},{"name":"Eagle Valley Middle School","x":152,"y":199.1,"proficiency":0.17,"district":"CARSON CITY SCHOOL DISTRICT","city":"Carson City"},{"name":"Pershing County Middle School","x":173.8,"y":184.7,"proficiency":0.245,"district":"PERSHING COUNTY SCHOOL DISTRICT","city":"Lovelock"},{"name":"Virginia City Middle School","x":153.6,"y":196.6,"proficiency":0.15,"district":"STOREY COUNTY SCHOOL DISTRICT","city":"Virginia City"},{"name":"ARCHIE CLAYTON PRE-A.P. ACADEMY","x":152,"y":191.8,"proficiency":0.32,"district":"WASHOE COUNTY SCHOOL DISTRICT","city":"RENO"},{"name":"DARREL SWOPE MIDDLE SCHOOL","x":151.8,"y":192.3,"proficiency":0.32,"district":"WASHOE COUNTY SCHOOL DISTRICT","city":"RENO"},{"name":"E. OTIS VAUGHN MIDDLE SCHOOL","x":152.6,"y":192.4,"proficiency":0.025,"district":"WASHOE COUNTY SCHOOL DISTRICT","city":"RENO"},{"name":"EDWARD L. PINE MIDDLE SCHOOL","x":152.6,"y":193.1,"proficiency":0.15,"district":"WASHOE COUNTY SCHOOL DISTRICT","city":"RENO"},{"name":"FRED W. TRANER MIDDLE SCHOOL","x":152.7,"y":191.9,"proficiency":0.075,"district":"WASHOE COUNTY SCHOOL DISTRICT","city":"RENO"},{"name":"GEORGE L. DILWORTH S.T.E.M ACADEMY","x":153.4,"y":192.1,"proficiency":0.12,"district":"WASHOE COUNTY SCHOOL DISTRICT","city":"SPARKS"},{"name":"WILLIAM OBRIEN MIDDLE SCHOOL","x":151.9,"y":190.1,"proficiency":0.075,"district":"WASHOE COUNTY SCHOOL DISTRICT","city":"RENO"},{"name":"SPARKS MIDDLE SCHOOL","x":153.1,"y":191.8,"proficiency":0.12,"district":"WASHOE COUNTY SCHOOL DISTRICT","city":"SPARKS"},{"name":"INCLINE MIDDLE SCHOOL","x":149.2,"y":196.7,"proficiency":0.245,"district":"WASHOE COUNTY SCHOOL DISTRICT","city":"INCLINE VILLAGE"},{"name":"MOUNT ROSE K-8 ACADEMY OF LANGUAGES","x":152.3,"y":192.3,"proficiency":0.845,"district":"WASHOE COUNTY SCHOOL DISTRICT","city":"RENO"},{"name":"BILLINGHURST MIDDLE SCHOOL","x":151.2,"y":191.9,"proficiency":0.26,"district":"WASHOE COUNTY SCHOOL DISTRICT","city":"RENO"},{"name":"LOU MENDIVE MIDDLE SCHOOL","x":154,"y":192,"proficiency":0.22,"district":"WASHOE COUNTY SCHOOL DISTRICT","city":"SPARKS"},{"name":"Sierra Nevada Academy Charter","x":152,"y":189.8,"proficiency":0.05,"district":"WASHOE COUNTY SCHOOL DISTRICT","city":"RENO"},{"name":"High Desert Montessori","x":152.9,"y":191.8,"proficiency":0.1,"district":"WASHOE COUNTY SCHOOL DISTRICT","city":"RENO"},{"name":"YVONNE SHAW MIDDLE SCHOOL","x":154.2,"y":190.2,"proficiency":0.32,"district":"WASHOE COUNTY SCHOOL DISTRICT","city":"SPARKS"},{"name":"COLD SPRINGS MIDDLE SCHOOL","x":151.1,"y":188.5,"proficiency":0.12,"district":"WASHOE COUNTY SCHOOL DISTRICT","city":"RENO"},{"name":"KENDYL DEPOALI MIDDLE SCHOOL","x":153.1,"y":193.8,"proficiency":0.39,"district":"WASHOE COUNTY SCHOOL DISTRICT","city":"RENO"},{"name":"NORTH STAR ONLINE SCHOOL","x":152.7,"y":193.2,"proficiency":0.545,"district":"WASHOE COUNTY SCHOOL DISTRICT","city":"RENO"},{"name":"Coral Academy Middle School","x":152.7,"y":191.9,"proficiency":0.37,"district":"WASHOE COUNTY SCHOOL DISTRICT","city":"RENO"},{"name":"SKY RANCH MIDDLE SCHOOL","x":154,"y":190.9,"proficiency":0.36,"district":"WASHOE COUNTY SCHOOL DISTRICT","city":"SPARKS"},{"name":"DESERT SKIES MIDDLE SCHOOL","x":153.5,"y":190.5,"proficiency":0.11,"district":"WASHOE COUNTY SCHOOL DISTRICT","city":"SUN VALLEY"},{"name":"MARCE HERZ MIDDLE SCHOOL","x":152.1,"y":194.4,"proficiency":0.47,"district":"WASHOE COUNTY SCHOOL DISTRICT","city":"RENO"},{"name":"White Pine Middle School","x":219.8,"y":212.9,"proficiency":0.17,"district":"WHITE PINE COUNTY SCHOOL DISTRICT","city":"Ely"},{"name":"Lund High School","x":216.8,"y":219.7,"proficiency":0.245,"district":"WHITE PINE COUNTY SCHOOL DISTRICT","city":"Lund"}],"districts":[{"name":"STATE-SPONSORED CHARTER SCHOOLS","x":200.3,"y":259.5,"proficiency":0.2823,"schoolCount":45},{"name":"DAVIDSON ACADEMY  SCHOOL DISTRICT","x":152.4,"y":191.9,"proficiency":0.9,"schoolCount":1},{"name":"CHURCHILL COUNTY SCHOOL DISTRICT","x":166.5,"y":196.7,"proficiency":0.12,"schoolCount":1},{"name":"CLARK COUNTY SCHOOL DISTRICT","x":204.8,"y":269.5,"proficiency":0.1728,"schoolCount":65},{"name":"DOUGLAS COUNTY SCHOOL DISTRICT","x":150.1,"y":202.7,"proficiency":0.285,"schoolCount":4},{"name":"ELKO COUNTY SCHOOL DISTRICT","x":219.9,"y":176.9,"proficiency":0.1275,"schoolCount":8},{"name":"ESMERALDA COUNTY SCHOOL DISTRICT","x":168.4,"y":231.4,"proficiency":0.245,"schoolCount":1},{"name":"EUREKA COUNTY SCHOOL DISTRICT","x":205.8,"y":204.9,"proficiency":0.1,"schoolCount":1},{"name":"HUMBOLDT COUNTY SCHOOL DISTRICT","x":187.5,"y":172.6,"proficiency":0.32,"schoolCount":1},{"name":"LANDER COUNTY SCHOOL DISTRICT","x":196.6,"y":181.1,"proficiency":0.17,"schoolCount":1},{"name":"LINCOLN COUNTY SCHOOL DISTRICT","x":215.2,"y":244.1,"proficiency":0.2725,"schoolCount":2},{"name":"LYON COUNTY SCHOOL DISTRICT","x":157.9,"y":199.8,"proficiency":0.146,"schoolCount":5},{"name":"MINERAL COUNTY SCHOOL DISTRICT","x":164.3,"y":214.5,"proficiency":0.05,"schoolCount":1},{"name":"NYE COUNTY SCHOOL DISTRICT","x":187.5,"y":253.2,"proficiency":0.172,"schoolCount":5},{"name":"CARSON CITY SCHOOL DISTRICT","x":151.6,"y":199,"proficiency":0.18,"schoolCount":2},{"name":"PERSHING COUNTY SCHOOL DISTRICT","x":173.8,"y":184.7,"proficiency":0.245,"schoolCount":1},{"name":"STOREY COUNTY SCHOOL DISTRICT","x":153.6,"y":196.6,"proficiency":0.15,"schoolCount":1},{"name":"WASHOE COUNTY SCHOOL DISTRICT","x":152.5,"y":192,"proficiency":0.255,"schoolCount":22},{"name":"WHITE PINE COUNTY SCHOOL DISTRICT","x":218.3,"y":216.3,"proficiency":0.2075,"schoolCount":2}],"cities":[{"name":"Las Vegas","x":204,"y":269.1,"lat":36.158172739130436,"lon":-115.18527460869565,"proficiency":0.1989,"schoolCount":69},{"name":"Henderson","x":205.6,"y":272,"lat":36.0246739375,"lon":-115.04132824999999,"proficiency":0.3237,"schoolCount":16},{"name":"Elko","x":213.6,"y":181,"lat":40.84040866666667,"lon":-115.77559766666667,"proficiency":0.2417,"schoolCount":3},{"name":"Fallon","x":166.4,"y":196.6,"lat":39.473102999999995,"lon":-118.78338249999999,"proficiency":0.3325,"schoolCount":2},{"name":"Reno","x":152.5,"y":192.7,"lat":39.498240249999995,"lon":-119.798489,"proficiency":0.4913,"schoolCount":4},{"name":"Ely","x":220.1,"y":212.9,"lat":39.249886000000004,"lon":-114.874587,"proficiency":0.135,"schoolCount":2},{"name":"North Las Vegas","x":204.8,"y":267.4,"lat":36.25396416666667,"lon":-115.15680066666665,"proficiency":0.1708,"schoolCount":6},{"name":"N  Las Vegas","x":204.8,"y":267.7,"lat":36.23964685714286,"lon":-115.15211928571429,"proficiency":0.0921,"schoolCount":7},{"name":"Overton","x":216.2,"y":264.2,"lat":36.541734,"lon":-114.448435,"proficiency":0.47,"schoolCount":1},{"name":"Boulder City","x":208.5,"y":273.7,"lat":35.969715,"lon":-114.832705,"proficiency":0.22,"schoolCount":1},{"name":"Sandy Valley","x":196.5,"y":274.2,"lat":35.813294,"lon":-115.610032,"proficiency":0.1,"schoolCount":1},{"name":"Laughlin","x":208.7,"y":289.2,"lat":35.163729,"lon":-114.614471,"proficiency":0.05,"schoolCount":1},{"name":"Mesquite","x":222.4,"y":260.5,"lat":36.795645,"lon":-114.082861,"proficiency":0.22,"schoolCount":1},{"name":"Indian Springs","x":198.4,"y":260,"lat":36.574247,"lon":-115.676645,"proficiency":0.1,"schoolCount":1},{"name":"Gardnerville","x":150.6,"y":203.5,"lat":38.915886,"lon":-119.737417,"proficiency":0.27,"schoolCount":2},{"name":"Zephyr Cove","x":148.2,"y":201,"lat":39.013978,"lon":-119.942119,"proficiency":0.3,"schoolCount":1},{"name":"Minden","x":150.9,"y":202.8,"lat":38.959323,"lon":-119.730078,"proficiency":0.3,"schoolCount":1},{"name":"Spring Creek","x":215.1,"y":182.5,"lat":40.777136,"lon":-115.645719,"proficiency":0.17,"schoolCount":1},{"name":"Carlin","x":208.5,"y":182.3,"lat":40.716797,"lon":-116.110229,"proficiency":0.1,"schoolCount":1},{"name":"Owyhee","x":213.6,"y":159.7,"lat":41.943123,"lon":-116.097321,"proficiency":0.1,"schoolCount":1},{"name":"Wells","x":225.7,"y":178.3,"lat":41.108354,"lon":-114.970202,"proficiency":0.1,"schoolCount":1},{"name":"Jackpot","x":233,"y":163,"lat":41.982371,"lon":-114.668852,"proficiency":0.245,"schoolCount":1},{"name":"West Wendover","x":236.5,"y":187.7,"lat":40.732983,"lon":-114.081116,"proficiency":0.075,"schoolCount":1},{"name":"Dyer","x":168.4,"y":231.4,"lat":37.704854,"lon":-118.086476,"proficiency":0.245,"schoolCount":1},{"name":"Eureka","x":205.8,"y":204.9,"lat":39.514075,"lon":-115.96722,"proficiency":0.1,"schoolCount":1},{"name":"Winnemucca","x":187.5,"y":172.6,"lat":40.974813,"lon":-117.729321,"proficiency":0.32,"schoolCount":1},{"name":"Battle Mountain","x":196.6,"y":181.1,"lat":40.640967,"lon":-116.954873,"proficiency":0.17,"schoolCount":1},{"name":"Panaca","x":221.6,"y":241.2,"lat":37.791361,"lon":-114.387746,"proficiency":0.245,"schoolCount":1},{"name":"Alamo","x":208.8,"y":247,"lat":37.361766,"lon":-115.165017,"proficiency":0.3,"schoolCount":1},{"name":"Smith","x":155.8,"y":207,"lat":38.80267,"lon":-119.327526,"proficiency":0.1,"schoolCount":1},{"name":"Yerington","x":159,"y":204.2,"lat":38.990073,"lon":-119.159565,"proficiency":0.17,"schoolCount":1},{"name":"Dayton","x":154.3,"y":198.2,"lat":39.239366,"lon":-119.576423,"proficiency":0.17,"schoolCount":1},{"name":"Silver Springs","x":159.1,"y":196.4,"lat":39.390878,"lon":-119.283588,"proficiency":0.17,"schoolCount":1},{"name":"Fernley","x":161.2,"y":193.1,"lat":39.590958,"lon":-119.195562,"proficiency":0.12,"schoolCount":1},{"name":"Hawthorne","x":164.3,"y":214.5,"lat":38.526407,"lon":-118.629443,"proficiency":0.05,"schoolCount":1},{"name":"Pahrump","x":192.3,"y":265.2,"lat":36.2358585,"lon":-116.0081745,"proficiency":0.135,"schoolCount":2},{"name":"Amargosa","x":187,"y":257.6,"lat":36.569404,"lon":-116.461016,"proficiency":0.245,"schoolCount":1},{"name":"Beatty","x":184,"y":250.4,"lat":36.907381,"lon":-116.762877,"proficiency":0.245,"schoolCount":1},{"name":"Tonopah","x":182.1,"y":227.7,"lat":38.061129,"lon":-117.232703,"proficiency":0.1,"schoolCount":1},{"name":"Carson City","x":151.6,"y":199,"lat":39.161874499999996,"lon":-119.7486135,"proficiency":0.18,"schoolCount":2},{"name":"Lovelock","x":173.8,"y":184.7,"lat":40.183187,"lon":-118.478465,"proficiency":0.245,"schoolCount":1},{"name":"Virginia City","x":153.6,"y":196.6,"lat":39.309015,"lon":-119.649175,"proficiency":0.15,"schoolCount":1},{"name":"RENO","x":152.3,"y":191.9,"lat":39.5327912,"lon":-119.82493086666666,"proficiency":0.2743,"schoolCount":15},{"name":"SPARKS","x":153.7,"y":191.4,"lat":39.5804162,"lon":-119.7333654,"proficiency":0.228,"schoolCount":5},{"name":"INCLINE VILLAGE","x":149.2,"y":196.7,"lat":39.246856,"lon":-119.946913,"proficiency":0.245,"schoolCount":1},{"name":"SUN VALLEY","x":153.5,"y":190.5,"lat":39.622181,"lon":-119.764915,"proficiency":0.11,"schoolCount":1},{"name":"Lund","x":216.8,"y":219.7,"lat":38.862055,"lon":-114.999657,"proficiency":0.245,"schoolCount":1}]}